[
  {
    "если": [
      {
        "атрибут": "тип",
        "значение": "командный"
      },
      {
        "атрибут": "инвентарь",
        "значение": "мяч"
      },
      {
        "атрибут": "игровое покрытие",
        "значение": "паркет"
      },
      {
        "атрибут": "размер команды",
        "значение": "6"
      }
    ],
    "то": {
      "атрибут": "вид",
      "значение": "волейбол"
    }
  },
  {
    "если": [
      {
        "атрибут": "тип",
        "значение": "командный"
      },
      {
        "атрибут": "инвентарь",
        "значение": "мяч"
      },
      {
        "атрибут": "игровое покрытие",
        "значение": "паркет"
      },
      {
        "атрибут": "размер команды",
        "значение": "5"
      }
    ],
    "то": {
      "атрибут": "вид",
      "значение": "баскетбол"
    }
  },
  {
    "если": [
      {
        "атрибут": "тип",
        "значение": "командный"
      },
      {
        "атрибут": "инвентарь",
        "значение": "мяч"
      },
      {
        "атрибут": "игровое покрытие",
        "значение": "песок"
      },
      {
        "атрибут": "размер команды",
        "значение": "2"
      }
    ],
    "то": {
      "атрибут": "вид",
      "значение": "пляжный волейбол"
    }
  },
  {
    "если": [
      {
        "атрибут": "тип",
        "значение": "командный"
      },
      {
        "атрибут": "инвентарь",
        "значение": "мяч"
      },
      {
        "атрибут": "игровое покрытие",
        "значение": "трава"
      }
    ],
    "то": {
      "атрибут": "вид",
      "значение": "футбол"
    }
  },
  {
    "если": [
      {
        "атрибут": "тип",
        "значение": "командный"
      },
      {
        "атрибут": "инвентарь",
        "значение": "шайба"
      },
      {
        "атрибут": "игровое покрытие",
        "значение": "лед"
      },
      {
        "атрибут": "размер команды",
        "значение": "6"
      }
    ],
    "то": {
      "атрибут": "вид",
      "значение": "хоккей"
    }
  },
  {
    "если": [
      {
        "атрибут": "тип",
        "значение": "индивидуальный"
      },
      {
        "атрибут": "инвентарь",
        "значение": "мяч"
      },
      {
        "атрибут": "игровое покрытие",
        "значение": "трава"
      }
    ],
    "то": {
      "атрибут": "вид",
      "значение": "гольф"
    }
  },
  {
    "если": [
      {
        "атрибут": "тип",
        "значение": "индивидуальный"
      },
      {
        "атрибут": "инвентарь",
        "значение": "дротик"
      }
    ],
    "то": {
      "атрибут": "вид",
      "значение": "дартс"
    }
  },
  {
    "если": [
      {
        "атрибут": "тип",
        "значение": "командный"
      },
      {
        "атрибут": "игровое покрытие",
        "значение": "песок"
      }
    ],
    "то": {
      "атрибут": "инвентарь",
      "значение": "мяч"
    }
  },
  {
    "если": [
      {
        "атрибут": "тип",
        "значение": "командный"
      },
      {
        "атрибут": "игровое покрытие",
        "значение": "лед"
      },
      {
        "атрибут": "размер команды",
        "значение": "4"
      }
    ],
    "то": {
      "атрибут": "инвентарь",
      "значение": "щетка"
    }
  },
  {
    "если": [
      {
        "атрибут": "сезон",
        "значение": "лето"
      },
      {
        "атрибут": "вид",
        "значение": "гольф"
      }
    ],
    "то": {
      "атрибут": "олимпийский",
      "значение": "нет"
    }
  },
  {
    "если": [
      {
        "атрибут": "сезон",
        "значение": "лето"
      },
      {
        "атрибут": "вид",
        "значение": "плавание"
      }
    ],
    "то": {
      "атрибут": "олимпийский",
      "значение": "да"
    }
  },
  {
    "если": [
      {
        "атрибут": "сезон",
        "значение": "лето"
      },
      {
        "атрибут": "вид",
        "значение": "стрельба"
      },
      {
        "атрибут": "инвентарь",
        "значение": "лук"
      }
    ],
    "то": {
      "атрибут": "олимпийский",
      "значение": "да"
    }
  },
  {
    "если": [
      {
        "атрибут": "сезон",
        "значение": "зима"
      },
      {
        "атрибут": "вид",
        "значение": "керлинг"
      }
    ],
    "то": {
      "атрибут": "олимпийский",
      "значение": "да"
    }
  },
  {
    "если": [
      {
        "атрибут": "сезон",
        "значение": "зима"
      },
      {
        "атрибут": "вид",
        "значение": "хоккей"
      }
    ],
    "то": {
      "атрибут": "олимпийский",
      "значение": "да"
    }
  },
  {
    "если": [
      {
        "атрибут": "сезон",
        "значение": "зима"
      },
      {
        "атрибут": "вид",
        "значение": "лыжный"
      },
      {
        "атрибут": "инвентарь",
        "значение": "сноуборд"
      }
    ],
    "то": {
      "атрибут": "олимпийский",
      "значение": "да"
    }
  }
]